p_ages-1.0.1.dist-info/DESCRIPTION.rst
p_ages-1.0.1.dist-info/METADATA
p_ages-1.0.1.dist-info/RECORD
p_ages-1.0.1.dist-info/WHEEL
p_ages-1.0.1.dist-info/metadata.json
p_ages-1.0.1.dist-info/top_level.txt
pages/__init__.py
pages/element_with_language.py
pages/element_with_traits.py
pages/exceptions.py
pages/loadable_element.py
pages/page.py
pages/traits.py
pages/ui_component.py
pages/standard_components/__init__.py
pages/standard_components/button.py
pages/standard_components/checkbox.py
pages/standard_components/dropdown.py
pages/standard_components/image.py
pages/standard_components/label.py
pages/standard_components/link.py
pages/standard_components/radiobutton.py
pages/standard_components/table.py
pages/standard_components/textinput.py
pages/wait/__init__.py
pages/wait/wait.py
