Metadata-Version: 2.0
Name: p-ages
Version: 1.0.1
Summary: pages is a lightweight page object and component Python library for UI tests
Home-page: https://github.com/Skyscanner/pages
Author: valerio morsella
Author-email: valerio.morsella@skyscanner.net
License: ASL v.2.0
Platform: UNKNOWN
Classifier: Development Status :: 5 - Production/Stable
Classifier: Intended Audience :: Developers
Classifier: Programming Language :: Python :: 2.7
Classifier: Topic :: Software Development :: Libraries :: Python Modules
Classifier: Topic :: Software Development :: Testing
Requires-Dist: selenium
